DIS_lab/lab7/jkflipflop/jkflipflop.v
module jkflipflop(J, K, Clock, Resetn, Q);
input J, K, Clock, Resetn;
output reg Q;
always @(posedge Clock)
begin
    if (Resetn) Q <= 1'b0;
    else if (J && !K) Q <= 1'b1;
    else if (!J && K) Q <= 1'b0;
    else if (J && K) Q <= ~Q;
end
endmodule

DIS_lab/lab7/jkflipflop/testbench.v
`timescale 1ns/1ns
`include "jkflipflop.v"

module testbench();
reg J, K, Clock, Resetn;
wire Q;

jkflipflop FF(J, K, Clock, Resetn, Q);
initial begin
    $dumpfile("jkflipflop.vcd");
    $dumpvars(0,testbench);
    Clock = 0;
    forever #20 Clock = ~Clock;
end
initial begin
    Resetn = 1; 
    J = 1; K = 0;
    #10 Resetn = 0;  

    #40; J = 1; K = 0;
    #40; J = 0; K = 1;
    #40; J = 1; K = 1;
    #40; J = 0; K = 0;

    $display("test complete");
    #20 $finish;
end
endmodule

DIS_lab/lab7/jkflipflop/jkflipflop.vcd
$date
	Fri Sep 26 10:52:51 2025
$end
$version
	Icarus Verilog
$end
$timescale
	1ns
$end
$scope module testbench $end
$var wire 1 ! Q $end
$var reg 1 " Clock $end
$var reg 1 # J $end
$var reg 1 $ K $end
$var reg 1 % Resetn $end
$scope module FF $end
$var wire 1 " Clock $end
$var wire 1 # J $end
$var wire 1 $ K $end
$var wire 1 % Resetn $end
$var reg 1 ! Q $end
$upscope $end
$upscope $end
$enddefinitions $end
#0
$dumpvars
1%
0$
1#
0"
x!
$end
#10
0%
#20
1!
1"
#40
0"
#60
1"
#80
0"
#90
1$
0#
#100
0!
1"
#120
0"
#130
1#
#140
1!
1"
#160
0"
#170
0$
0#
