DIS_lab/lab2/q3/q3.v
module q3(a,b,c,d,f);
    input a,b,c,d;
    output f;
    assign f = (a&b&d)|(a&b&c)|(b&c&d)|(a&c&d);
endmodule

DIS_lab/lab2/testbench.v
`timescale 1ns/1ns
`include "q3.v"

module testbench();
reg a,b,c,d;
wire f;

q3 q(a,b,c,d,f);
initial
begin
	$dumpfile("q3_tb.vcd");
	$dumpvars(0,testbench);
	
	a=1'b0;b=1'b0;c=1'b0;d=1'b0;
	#20;
	
	a=1'b0;b=1'b0;c=1'b0;d=1'b1;
	#20;
	
	a=1'b0;b=1'b0;c=1'b1;d=1'b0;
	#20;
	
	a=1'b0;b=1'b0;c=1'b1;d=1'b1;
	#20;
	
	a=1'b0;b=1'b1;c=1'b0;d=1'b0;
	#20;
	
	a=1'b0;b=1'b1;c=1'b0;d=1'b1;
	#20;
	
	a=1'b0;b=1'b1;c=1'b1;d=1'b0;
	#20;
	
	a=1'b0;b=1'b1;c=1'b1;d=1'b1;
	#20;
	
	a=1'b1;b=1'b0;c=1'b0;d=1'b0;
	#20;
	
	a=1'b1;b=1'b0;c=1'b0;d=1'b1;
	#20;
	
	a=1'b1;b=1'b0;c=1'b1;d=1'b0;
	#20;
	
	a=1'b1;b=1'b0;c=1'b1;d=1'b1;
	#20;
	
	a=1'b1;b=1'b1;c=1'b0;d=1'b0;
	#20;
	
	a=1'b1;b=1'b1;c=1'b0;d=1'b1;
	#20;
	
	a=1'b1;b=1'b1;c=1'b1;d=1'b0;
	#20;
	
	a=1'b1;b=1'b1;c=1'b1;d=1'b1;
	#20;
	
	$display("test complete");
end
endmodule

DIS_lab/lab2/q3/q3_tb.vcd
$date
	Fri Aug  8 12:10:27 2025
$end
$version
	Icarus Verilog
$end
$timescale
	1ns
$end
$scope module testbench $end
$var wire 1 ! f $end
$var reg 1 " a $end
$var reg 1 # b $end
$var reg 1 $ c $end
$var reg 1 % d $end
$scope module q $end
$var wire 1 " a $end
$var wire 1 # b $end
$var wire 1 $ c $end
$var wire 1 % d $end
$var wire 1 ! f $end
$upscope $end
$upscope $end
$enddefinitions $end
#0
$dumpvars
0%
0$
0#
0"
0!
$end
#20
1%
#40
0%
1$
#60
1%
#80
0%
0$
1#
#100
1%
#120
0%
1$
#140
1!
1%
#160
0!
0%
0$
0#
1"
#180
1%
#200
0%
1$
#220
1!
1%
#240
0!
0%
0$
1#
#260
1!
1%
#280
0%
1$
#300
1%
