DIS_lab/lab9/q2/tflipflop.v
module tflipflop(T, Clk, Resetn, Q);
input T, Clk, Resetn;
output reg Q;
always @(negedge Clk or negedge Resetn)
begin
    if (!Resetn) Q <= 1'b0;
    else if (T) Q <= ~Q;
end
endmodule

DIS_lab/lab9/q2/q2.v
`include "tflipflop.v"

module q2(x,Clk,Resetn,A,B);
    wire Ta, Tb;
    input x, Clk, Resetn;
    output A, B;
    assign Ta =  ~A&B|B&~x;
    assign Tb = ~B&~x | A&~x | ~A&B&x;
    tflipflop tff1(Ta, Clk, Resetn, A);
    tflipflop tff2(Tb, Clk, Resetn, B);
endmodule

DIS_lab/lab9/q2/testbench.v
`include "q2.v"
`timescale 1ns/1ns

module testbench();
reg x, Clk, Resetn;
wire A, B;
q2 q(x, Clk, Resetn, A, B);

initial begin
    $dumpfile("q2.vcd");
    $dumpvars(0,testbench);

    Clk = 0;
    forever #10 Clk = ~Clk;
end
initial begin
    Resetn = 0; #15;
    Resetn = 1;
end
initial begin
    x=0;#80;
    x=1;#20;
    x=0;#20;
    x=1;#20;
    x=0;#20;
    x=1;#20;
    $display("test complete");
    #10 $finish;
end
endmodule

DIS_lab/lab9/q2/q2.vcd
$date
	Fri Oct 10 11:52:18 2025
$end
$version
	Icarus Verilog
$end
$timescale
	1ns
$end
$scope module testbench $end
$var wire 1 ! B $end
$var wire 1 " A $end
$var reg 1 # Clk $end
$var reg 1 $ Resetn $end
$var reg 1 % x $end
$scope module q $end
$var wire 1 # Clk $end
$var wire 1 $ Resetn $end
$var wire 1 & Ta $end
$var wire 1 ' Tb $end
$var wire 1 % x $end
$var wire 1 ! B $end
$var wire 1 " A $end
$scope module tff1 $end
$var wire 1 # Clk $end
$var wire 1 $ Resetn $end
$var wire 1 & T $end
$var reg 1 " Q $end
$upscope $end
$scope module tff2 $end
$var wire 1 # Clk $end
$var wire 1 $ Resetn $end
$var wire 1 ' T $end
$var reg 1 ! Q $end
$upscope $end
$upscope $end
$upscope $end
$enddefinitions $end
#0
$dumpvars
1'
0&
0%
0$
0#
0"
0!
$end
#10
1#
#15
1$
#20
0'
1&
1!
0#
#30
1#
#40
1'
1"
0#
#50
1#
#60
1'
0&
0!
0"
0#
#70
1#
#80
1&
1!
1'
0#
1%
#90
1#
#100
0&
0!
1"
1'
0#
0%
#110
1#
#120
1!
0'
0#
1%
#130
1#
#140
1'
1&
0#
0%
#150
1#
#160
0"
0!
0'
0&
0#
1%
