DIS_lab/week1/gate2/gate2.v
module gate2(a,b,c,d,f);
	input a,b,c,d;
	output f;
	assign f = (a|b)&(c|d);
endmodule

DIS_lab/week1/gate2/gate2_tb.v
`timescale 1ns/1ns
`include "gate2.v"

module gate2_tb();
reg a,b,c,d;
wire f;

gate2 g2(a,b,c,d,f);
initial
begin
	$dumpfile("gate2_tb.vcd");
	$dumpvars(0,gate2_tb);
	
	a=1'b0;b=1'b0;c=1'b0;d=1'b0;
	#15;
	
	a=1'b0;b=1'b0;c=1'b0;d=1'b1;
	#15;
	
	a=1'b0;b=1'b0;c=1'b1;d=1'b0;
	#15;
	
	a=1'b0;b=1'b0;c=1'b1;d=1'b1;
	#15;
	
	a=1'b0;b=1'b1;c=1'b0;d=1'b0;
	#15;
	
	a=1'b0;b=1'b1;c=1'b0;d=1'b1;
	#15;
	
	a=1'b0;b=1'b1;c=1'b1;d=1'b0;
	#15;
	
	a=1'b0;b=1'b1;c=1'b1;d=1'b1;
	#15;
	
	a=1'b1;b=1'b0;c=1'b0;d=1'b0;
	#15;
	
	a=1'b1;b=1'b0;c=1'b0;d=1'b1;
	#15;
	
	a=1'b1;b=1'b0;c=1'b1;d=1'b0;
	#15;
	
	a=1'b1;b=1'b0;c=1'b1;d=1'b1;
	#15;
	$display("test complete");
end
endmodule

DIS_lab/week1/gate2/gate2_tb.vcd
$date
	Fri Jul 25 11:52:11 2025
$end
$version
	Icarus Verilog
$end
$timescale
	1ns
$end
$scope module gate2_tb $end
$var wire 1 ! f $end
$var reg 1 " a $end
$var reg 1 # b $end
$var reg 1 $ c $end
$var reg 1 % d $end
$scope module g2 $end
$var wire 1 " a $end
$var wire 1 # b $end
$var wire 1 $ c $end
$var wire 1 % d $end
$var wire 1 ! f $end
$upscope $end
$upscope $end
$enddefinitions $end
#0
$dumpvars
0%
0$
0#
0"
0!
$end
#15
1%
#30
0%
1$
#45
1%
#60
0%
0$
1#
#75
1!
1%
#90
0%
1$
#105
1%
#120
0!
0%
0$
0#
1"
#135
1!
1%
#150
0%
1$
#165
1%
