DIS_lab/lab6/priorityencoder16x4/priorityencoder16x4.v
module priorityencoder16x4(w,y,z);
    input [15:0] w;
    output reg[3:0] y;
    output z;
    integer k;
    assign z = |w;
    always @(w)
    begin
        y = 2'bxx;
        for(k = 0; k < 16; k = k+1)
        if(w[k] == 1)y = k;
    end
endmodule

DIS_lab/lab6/priorityencoder16x4/testbench.v
`timescale 1ns/1ns
`include "priorityencoder16x4.v"

module testbench();
reg [15:0] w;
wire [3:0]y;
wire z;
priorityencoder16x4 e(w,y,z);
initial
begin
	$dumpfile("priorityencoder16x4.vcd");
	$dumpvars(0,testbench);
	
	w=16'b1111111111111111;
	#20;
	
	w=16'b0000000000000000;
	#20;
	
	w=16'b0001110101010101;
	#20;
	
	w=16'b0011101010101011;
	#20;
	
	w=16'b0000000010101011;
	#20;
	
	w=16'b0000010010101011;
	#20;
	
	w=16'b0000000000000001;
	#20;
	
	w=16'b0000000000001011;
	#20;

	$display("test complete");
end
endmodule

DIS_lab/lab6/priorityencoder16x4/priorityencoder16x4.vcd
$date
	Fri Sep 19 11:17:14 2025
$end
$version
	Icarus Verilog
$end
$timescale
	1ns
$end
$scope module testbench $end
$var wire 1 ! z $end
$var wire 4 " y [3:0] $end
$var reg 16 # w [15:0] $end
$scope module e $end
$var wire 16 $ w [15:0] $end
$var wire 1 ! z $end
$var reg 4 % y [3:0] $end
$var integer 32 & k [31:0] $end
$upscope $end
$upscope $end
$enddefinitions $end
#0
$dumpvars
b10000 &
b1111 %
b1111111111111111 $
b1111111111111111 #
b1111 "
1!
$end
#20
b10000 &
b0xx "
b0xx %
0!
b0 #
b0 $
#40
b1100 "
b1100 %
b10000 &
1!
b1110101010101 #
b1110101010101 $
#60
b10000 &
b1101 "
b1101 %
b11101010101011 #
b11101010101011 $
#80
b10000 &
b111 "
b111 %
b10101011 #
b10101011 $
#100
b10000 &
b1010 "
b1010 %
b10010101011 #
b10010101011 $
#120
b10000 &
b0 "
b0 %
b1 #
b1 $
#140
b10000 &
b11 "
b11 %
b1011 #
b1011 $
