DIS_lab/lab5/mux16x1_with_8x1/mux2x1.v
module mux2x1(w,s,out);
    input [1:0] w;
    input s;
    output reg out;

    always@(w or s)
    begin
        case (s)
            1'b0:out = w[0];
            1'b1:out = w[1]; 
        endcase
    end
endmodule

DIS_lab/lab5/mux16x1_with_8x1/mux8x1.v
module mux8x1(w,s,out);
    input [7:0] w;
    input [2:0] s;
    output reg out;

    always@(w or s)
    begin
        case (s)
            3'b000: out = w[0];
            3'b001: out = w[1];
            3'b010: out = w[2];
            3'b011: out = w[3];
            3'b100: out = w[4];
            3'b101: out = w[5];
            3'b110: out = w[6];
            3'b111: out = w[7];
        endcase
    end
endmodule

DIS_lab/lab5/mux16x1_with_8x1/mux16x1.v
`include "mux2x1.v"
`include "mux8x1.v"

module mux16x1(w,s,out);
    input [15:0] w;
    input [3:0] s;
    output out;
    wire m0out,m1out;

    mux8x1 m0(w[7:0],s[2:0],m0out);
    mux8x1 m1(w[15:8],s[2:0],m1out);
    mux2x1 m2({m1out,m0out},s[3],out);
endmodule

DIS_lab/lab5/mux16x1_with_8x1/testbench.v
`timescale 1ns/1ns
`include "mux16x1.v"

module testbench();
reg [15:0] w;
reg [3:0] s;
wire out;

mux16x1 m(w,s,out);
initial
begin
    $dumpfile("mux16x1.vcd");
    $dumpvars(0,testbench);

    w = 16'b1011101101001101; s=4'b0000;
    #20;

    w = 16'b1011101101001101; s=4'b0001;
    #20;

    w = 16'b1011101101001101; s=4'b0010;
    #20;

    w = 16'b1011101101001101; s=4'b0011;
    #20;

    w = 16'b1011101101001101; s=4'b0100;
    #20;

    w = 16'b1011101101001101; s=4'b0101;
    #20;

    w = 16'b1011101101001101; s=4'b0110;
    #20;

    w = 16'b1011101101001101; s=4'b0111;
    #20;
    
    w = 16'b1011101101001101; s=4'b1000;
    #20;

    w = 16'b1011101101001101; s=4'b1001;
    #20;

    w = 16'b1011101101001101; s=4'b1010;
    #20;

    w = 16'b1011101101001101; s=4'b1011;
    #20;
    
    w = 16'b1011101101001101; s=4'b1100;
    #20;

    w = 16'b1011101101001101; s=4'b1101;
    #20;

    w = 16'b1011101101001101; s=4'b1110;
    #20;

    w = 16'b1011101101001101; s=4'b1111;
    #20;
    
    $display("test complete");
end
endmodule

DIS_lab/lab5/mux16x1_with_8x1/mux16x1.vcd
$date
	Fri Aug 29 11:49:19 2025
$end
$version
	Icarus Verilog
$end
$timescale
	1ns
$end
$scope module testbench $end
$var wire 1 ! out $end
$var reg 4 " s [3:0] $end
$var reg 16 # w [15:0] $end
$scope module m $end
$var wire 4 $ s [3:0] $end
$var wire 16 % w [15:0] $end
$var wire 1 ! out $end
$var wire 1 & m1out $end
$var wire 1 ' m0out $end
$scope module m0 $end
$var wire 3 ( s [2:0] $end
$var wire 8 ) w [7:0] $end
$var reg 1 ' out $end
$upscope $end
$scope module m1 $end
$var wire 3 * s [2:0] $end
$var wire 8 + w [7:0] $end
$var reg 1 & out $end
$upscope $end
$scope module m2 $end
$var wire 1 , s $end
$var wire 2 - w [1:0] $end
$var reg 1 ! out $end
$upscope $end
$upscope $end
$upscope $end
$enddefinitions $end
#0
$dumpvars
b11 -
0,
b10111011 +
b0 *
b1001101 )
b0 (
1'
1&
b1011101101001101 %
b0 $
b1011101101001101 #
b0 "
1!
$end
#20
0!
b10 -
0'
b1 (
b1 *
b1 "
b1 $
#40
1!
1'
b1 -
0&
b10 (
b10 *
b10 "
b10 $
#60
b11 -
1&
b11 (
b11 *
b11 "
b11 $
#80
0!
b10 -
0'
b100 (
b100 *
b100 "
b100 $
#100
b101 (
b101 *
b101 "
b101 $
#120
1!
1'
b1 -
0&
b110 (
b110 *
b110 "
b110 $
#140
0!
0'
b10 -
1&
b111 (
b111 *
b111 "
b111 $
#160
b11 -
1'
1!
b0 (
b0 *
1,
b1000 "
b1000 $
#180
b10 -
0'
b1 (
b1 *
b1001 "
b1001 $
#200
0!
1'
b1 -
0&
b10 (
b10 *
b1010 "
b1010 $
#220
1!
b11 -
1&
b11 (
b11 *
b1011 "
b1011 $
#240
b10 -
0'
b100 (
b100 *
b1100 "
b1100 $
#260
b101 (
b101 *
b1101 "
b1101 $
#280
0!
1'
b1 -
0&
b110 (
b110 *
b1110 "
b1110 $
#300
1!
0'
b10 -
1&
b111 (
b111 *
b1111 "
b1111 $
