DIS_lab/lab6/decoder4x16/decoder3x8.v
module decoder3x8(w,en,y);
    input [2:0] w;
    input en;
    output reg [7:0] y;
    integer k;

    always @(w or en)
    begin
        for(k = 0; k < 8; k = k+1)
        if((w == k) && (en == 1))
        y[k] = 1;
        else
        y[k] = 0;
    end
endmodule

DIS_lab/lab6/decoder4x16/decoder4x16.v
`include "decoder3x8.v"

module decoder4x16(w,en,y);
    input [3:0] w;
    input en;
    output [15:0] y;

    wire e1,e2;
    assign e1 = en&~w[3];
    assign e2 = en&w[3];

    decoder3x8 d1(w[2:0],e1,y[7:0]);
    decoder3x8 d2(w[2:0],e2,y[15:8]);
endmodule

DIS_lab/lab6/decoder4x16/testbench.v
`timescale 1ns/1ns
`include "decoder4x16.v"

module testbench();
reg [3:0] w;
reg en;
wire [15:0]y;

decoder4x16 d(w,en,y);
initial
begin
	$dumpfile("decoder4x16.vcd");
	$dumpvars(0,testbench);
	
	en=1'b0;w=4'b0000;
	#5;
	
	en=1'b0;w=4'b0001;
	#5;
	
	en=1'b0;w=4'b0010;
	#5;
	
	en=1'b0;w=4'b0011;
	#5;
	
	en=1'b0;w=4'b0100;
	#5;
	
	en=1'b0;w=4'b0101;
	#5;
	
	en=1'b0;w=4'b0110;
	#5;
	
	en=1'b0;w=4'b0111;
	#5;

    en=1'b0;w=4'b1000;
	#5;
	
	en=1'b0;w=4'b1001;
	#5;
	
	en=1'b0;w=4'b1010;
	#5;
	
	en=1'b0;w=4'b1011;
	#5;
	
	en=1'b0;w=4'b1100;
	#5;
	
	en=1'b0;w=4'b1101;
	#5;
	
	en=1'b0;w=4'b1110;
	#5;
	
	en=1'b0;w=4'b1111;
	#5;
	
	en=1'b1;w=4'b0000;
	#5;
	
	en=1'b1;w=4'b0001;
	#5;
	
	en=1'b1;w=4'b0010;
	#5;
	
	en=1'b1;w=4'b0011;
	#5;
	
	en=1'b1;w=4'b0100;
	#5;
	
	en=1'b1;w=4'b0101;
	#5;
	
	en=1'b1;w=4'b0110;
	#5;
	
	en=1'b1;w=4'b0111;
	#5;

    en=1'b1;w=4'b1000;
	#5;
	
	en=1'b1;w=4'b1001;
	#5;
	
	en=1'b1;w=4'b1010;
	#5;
	
	en=1'b1;w=4'b1011;
	#5;
	
	en=1'b1;w=4'b1100;
	#5;
	
	en=1'b1;w=4'b1101;
	#5;
	
	en=1'b1;w=4'b1110;
	#5;
	
	en=1'b1;w=4'b1111;
	#5;
	
	
	$display("test complete");
end
endmodule

DIS_lab/lab6/decoder4x16/decoder4x16.vcd
$date
	Fri Sep 19 10:42:35 2025
$end
$version
	Icarus Verilog
$end
$timescale
	1ns
$end
$scope module testbench $end
$var wire 16 ! y [15:0] $end
$var reg 1 " en $end
$var reg 4 # w [3:0] $end
$scope module d $end
$var wire 1 $ e1 $end
$var wire 1 % e2 $end
$var wire 1 " en $end
$var wire 4 & w [3:0] $end
$var wire 16 ' y [15:0] $end
$scope module d1 $end
$var wire 1 $ en $end
$var wire 3 ( w [2:0] $end
$var reg 8 ) y [7:0] $end
$var integer 32 * k [31:0] $end
$upscope $end
$scope module d2 $end
$var wire 1 % en $end
$var wire 3 + w [2:0] $end
$var reg 8 , y [7:0] $end
$var integer 32 - k [31:0] $end
$upscope $end
$upscope $end
$upscope $end
$enddefinitions $end
#0
$dumpvars
b1000 -
b0 ,
b0 +
b1000 *
b0 )
b0 (
b0 '
b0 &
0%
0$
b0 #
0"
b0 !
$end
#5
b1000 *
b1000 -
b1 (
b1 +
b1 #
b1 &
#10
b1000 *
b1000 -
b10 (
b10 +
b10 #
b10 &
#15
b1000 *
b1000 -
b11 (
b11 +
b11 #
b11 &
#20
b1000 *
b1000 -
b100 (
b100 +
b100 #
b100 &
#25
b1000 *
b1000 -
b101 (
b101 +
b101 #
b101 &
#30
b1000 *
b1000 -
b110 (
b110 +
b110 #
b110 &
#35
b1000 *
b1000 -
b111 (
b111 +
b111 #
b111 &
#40
b1000 *
b1000 -
b0 (
b0 +
b1000 #
b1000 &
#45
b1000 *
b1000 -
b1 (
b1 +
b1001 #
b1001 &
#50
b1000 *
b1000 -
b10 (
b10 +
b1010 #
b1010 &
#55
b1000 *
b1000 -
b11 (
b11 +
b1011 #
b1011 &
#60
b1000 *
b1000 -
b100 (
b100 +
b1100 #
b1100 &
#65
b1000 *
b1000 -
b101 (
b101 +
b1101 #
b1101 &
#70
b1000 *
b1000 -
b110 (
b110 +
b1110 #
b1110 &
#75
b1000 *
b1000 -
b111 (
b111 +
b1111 #
b1111 &
#80
b1 )
1$
b1000 *
b1 !
b1 '
b0 ,
b1000 -
b0 (
b0 +
0%
b0 #
b0 &
1"
#85
b10 !
b10 '
b10 )
b1000 *
b1000 -
b1 (
b1 +
b1 #
b1 &
#90
b100 !
b100 '
b100 )
b1000 *
b1000 -
b10 (
b10 +
b10 #
b10 &
#95
b1000 !
b1000 '
b1000 )
b1000 *
b1000 -
b11 (
b11 +
b11 #
b11 &
#100
b10000 !
b10000 '
b10000 )
b1000 *
b1000 -
b100 (
b100 +
b100 #
b100 &
#105
b100000 !
b100000 '
b100000 )
b1000 *
b1000 -
b101 (
b101 +
b101 #
b101 &
#110
b1000000 !
b1000000 '
b1000000 )
b1000 *
b1000 -
b110 (
b110 +
b110 #
b110 &
#115
b10000000 !
b10000000 '
b10000000 )
b1000 *
b1000 -
b111 (
b111 +
b111 #
b111 &
#120
0$
b1 ,
1%
b100000000 !
b100000000 '
b0 )
b1000 *
b1000 -
b0 (
b0 +
b1000 #
b1000 &
#125
b1000 *
b1000000000 !
b1000000000 '
b10 ,
b1000 -
b1 (
b1 +
b1001 #
b1001 &
#130
b1000 *
b10000000000 !
b10000000000 '
b100 ,
b1000 -
b10 (
b10 +
b1010 #
b1010 &
#135
b1000 *
b100000000000 !
b100000000000 '
b1000 ,
b1000 -
b11 (
b11 +
b1011 #
b1011 &
#140
b1000 *
b1000000000000 !
b1000000000000 '
b10000 ,
b1000 -
b100 (
b100 +
b1100 #
b1100 &
#145
b1000 *
b10000000000000 !
b10000000000000 '
b100000 ,
b1000 -
b101 (
b101 +
b1101 #
b1101 &
#150
b1000 *
b100000000000000 !
b100000000000000 '
b1000000 ,
b1000 -
b110 (
b110 +
b1110 #
b1110 &
#155
b1000 *
b1000000000000000 !
b1000000000000000 '
b10000000 ,
b1000 -
b111 (
b111 +
b1111 #
b1111 &
