DIS_lab/lab6/priorityencoder4x2/priorityencoder4x2.v
module priorityencoder4x2(w,y,z);
    input [3:0] w;
    output reg[1:0] y;
    output z;
    assign z = |w;
    always @(w)
    begin
        casex(w)
        4'b1xxx: y = 2'b11;
        4'b01xx: y = 2'b10;
        4'b001x: y = 2'b01;
        4'b0001: y = 2'b00;
        default: y = 2'bxx;
        endcase
    end
endmodule

DIS_lab/lab6/priorityencoder4x2/testbench.v
`timescale 1ns/1ns
`include "priorityencoder4x2.v"

module testbench();
reg [3:0] w;
wire [1:0]y;
wire z;
priorityencoder4x2 e(w,y,z);
initial
begin
	$dumpfile("priorityencoder4x2.vcd");
	$dumpvars(0,testbench);
	
	w=4'b0000;
	#20;
	
	w=4'b0001;
	#20;
	
	w=4'b0010;
	#20;
	
	w=4'b0011;
	#20;
	
	w=4'b0100;
	#20;
	
	w=4'b0101;
	#20;
	
	w=4'b0110;
	#20;
	
	w=4'b0111;
	#20;

    w=4'b1000;
	#20;
	
	w=4'b1001;
	#20;
	
	w=4'b1010;
	#20;
	
	w=4'b1011;
	#20;
	
	w=4'b1100;
	#20;
	
	w=4'b1101;
	#20;
	
	w=4'b1110;
	#20;
	
	w=4'b1111;
	#20;
	
	$display("test complete");
end
endmodule

DIS_lab/lab6/priorityencoder4x2/priorityencoder4x2.vcd
$date
	Fri Sep 19 11:07:36 2025
$end
$version
	Icarus Verilog
$end
$timescale
	1ns
$end
$scope module testbench $end
$var wire 1 ! z $end
$var wire 2 " y [1:0] $end
$var reg 4 # w [3:0] $end
$scope module e $end
$var wire 4 $ w [3:0] $end
$var wire 1 ! z $end
$var reg 2 % y [1:0] $end
$upscope $end
$upscope $end
$enddefinitions $end
#0
$dumpvars
bx %
b0 $
b0 #
bx "
0!
$end
#20
b0 "
b0 %
1!
b1 #
b1 $
#40
b1 "
b1 %
b10 #
b10 $
#60
b11 #
b11 $
#80
b10 "
b10 %
b100 #
b100 $
#100
b101 #
b101 $
#120
b110 #
b110 $
#140
b111 #
b111 $
#160
b11 "
b11 %
b1000 #
b1000 $
#180
b1001 #
b1001 $
#200
b1010 #
b1010 $
#220
b1011 #
b1011 $
#240
b1100 #
b1100 $
#260
b1101 #
b1101 $
#280
b1110 #
b1110 $
#300
b1111 #
b1111 $
