DIS_lab/lab6/decoder3x8/decoder2x4.v
module decoder2x4(w,en,y);
    input [1:0] w;
    input en;
    output reg [3:0] y;

    always @(w or en)
    begin
        if(en == 1'b0)
        y = 4'b0000;
        else
        begin
            if(w == 2'b00) y = 4'b0001;
            else if(w == 2'b01) y = 4'b0010;
            else if(w == 2'b10) y = 4'b0100;
            else y = 4'b1000;
        end
    end
endmodule

DIS_lab/lab6/decoder3x8/decoder3x8.v
`include "decoder2x4.v"

module decoder3x8(w,en,y);
    input [2:0] w;
    input en;
    output [7:0] y;

    wire e1,e2;
    assign e1 = en&~w[2];
    assign e2 = en&w[2];

    decoder2x4 d1(w[1:0],e1,y[3:0]);
    decoder2x4 d2(w[1:0],e2,y[7:4]);
endmodule

DIS_lab/lab6/decoder3x8/testbench.v
`timescale 1ns/1ns
`include "decoder3x8.v"

module testbench();
reg [2:0] w;
reg en;
wire [7:0]y;

decoder3x8 d(w,en,y);
initial
begin
	$dumpfile("decoder3x8.vcd");
	$dumpvars(0,testbench);
	
	en=1'b0;w=3'b000;
	#20;
	
	en=1'b0;w=3'b001;
	#20;
	
	en=1'b0;w=3'b010;
	#20;
	
	en=1'b0;w=3'b011;
	#20;
	
	en=1'b0;w=3'b100;
	#20;
	
	en=1'b0;w=3'b101;
	#20;
	
	en=1'b0;w=3'b110;
	#20;
	
	en=1'b0;w=3'b111;
	#20;
	
	en=1'b1;w=3'b000;
	#20;
	
	en=1'b1;w=3'b001;
	#20;
	
	en=1'b1;w=3'b010;
	#20;
	
	en=1'b1;w=3'b011;
	#20;
	
	en=1'b1;w=3'b100;
	#20;
	
	en=1'b1;w=3'b101;
	#20;
	
	en=1'b1;w=3'b110;
	#20;
	
	en=1'b1;w=3'b111;
	#20;
	
	$display("test complete");
end
endmodule

DIS_lab/lab6/decoder3x8/decoder3x8.vcd
$date
	Fri Sep 19 10:31:46 2025
$end
$version
	Icarus Verilog
$end
$timescale
	1ns
$end
$scope module testbench $end
$var wire 8 ! y [7:0] $end
$var reg 1 " en $end
$var reg 3 # w [2:0] $end
$scope module d $end
$var wire 1 $ e1 $end
$var wire 1 % e2 $end
$var wire 1 " en $end
$var wire 3 & w [2:0] $end
$var wire 8 ' y [7:0] $end
$scope module d1 $end
$var wire 1 $ en $end
$var wire 2 ( w [1:0] $end
$var reg 4 ) y [3:0] $end
$upscope $end
$scope module d2 $end
$var wire 1 % en $end
$var wire 2 * w [1:0] $end
$var reg 4 + y [3:0] $end
$upscope $end
$upscope $end
$upscope $end
$enddefinitions $end
#0
$dumpvars
b0 +
b0 *
b0 )
b0 (
b0 '
b0 &
0%
0$
b0 #
0"
b0 !
$end
#20
b1 (
b1 *
b1 #
b1 &
#40
b10 (
b10 *
b10 #
b10 &
#60
b11 (
b11 *
b11 #
b11 &
#80
b0 (
b0 *
b100 #
b100 &
#100
b1 (
b1 *
b101 #
b101 &
#120
b10 (
b10 *
b110 #
b110 &
#140
b11 (
b11 *
b111 #
b111 &
#160
b1 )
1$
b1 !
b1 '
b0 +
b0 (
b0 *
0%
b0 #
b0 &
1"
#180
b10 !
b10 '
b10 )
b1 (
b1 *
b1 #
b1 &
#200
b100 !
b100 '
b100 )
b10 (
b10 *
b10 #
b10 &
#220
b1000 !
b1000 '
b1000 )
b11 (
b11 *
b11 #
b11 &
#240
0$
b1 +
1%
b10000 !
b10000 '
b0 )
b0 (
b0 *
b100 #
b100 &
#260
b100000 !
b100000 '
b10 +
b1 (
b1 *
b101 #
b101 &
#280
b1000000 !
b1000000 '
b100 +
b10 (
b10 *
b110 #
b110 &
#300
b10000000 !
b10000000 '
b1000 +
b11 (
b11 *
b111 #
b111 &
