DIS_lab/lab8/johnson/dflipflop.v
module dflipflop(D, Clock, Resetn, Q);
input D, Clock, Resetn;
output reg Q;

always @(negedge Clock or negedge Resetn) begin
    if (!Resetn)
        Q <= 0;
    else
        Q <= D;
end

endmodule

DIS_lab/lab8/johnson/johnson.v

`include "dflipflop.v"
module johnson (clk, resetn, Q);
    input clk, resetn;
    output [4:0] Q;
    wire [4:0] D;

    assign D[0] = ~Q[4];
    assign D[4:1] = Q[3:0];

    dflipflop dff0 (D[0], clk, resetn, Q[0]);
    dflipflop dff1 (D[1], clk, resetn, Q[1]);
    dflipflop dff2 (D[2], clk, resetn, Q[2]);
    dflipflop dff3 (D[3], clk, resetn, Q[3]);
    dflipflop dff4 (D[4], clk, resetn, Q[4]);

endmodule

DIS_lab/lab8/johnson/testbench.v
`include "johnson.v"
`timescale 1ns/1ns

module testbench();
reg clk;
reg resetn;
wire [4:0] Q;

johnson jc(clk, resetn, Q);

initial begin
    $dumpfile("johnson.vcd");
    $dumpvars(0, testbench);
    clk = 0;
    resetn = 0;
    #15 resetn = 1;
    #200 $finish;
end

always #10 clk = ~clk;

initial begin
    $display("test complete");
end
endmodule

DIS_lab/lab8/johnson/johnson.vcd
$date
	Fri Oct  3 11:11:48 2025
$end
$version
	Icarus Verilog
$end
$timescale
	1ns
$end
$scope module testbench $end
$var wire 5 ! Q [4:0] $end
$var reg 1 " clk $end
$var reg 1 # resetn $end
$scope module jc $end
$var wire 1 " clk $end
$var wire 1 # resetn $end
$var wire 5 $ Q [4:0] $end
$var wire 5 % D [4:0] $end
$scope module dff0 $end
$var wire 1 " Clock $end
$var wire 1 & D $end
$var wire 1 # Resetn $end
$var reg 1 ' Q $end
$upscope $end
$scope module dff1 $end
$var wire 1 " Clock $end
$var wire 1 ( D $end
$var wire 1 # Resetn $end
$var reg 1 ) Q $end
$upscope $end
$scope module dff2 $end
$var wire 1 " Clock $end
$var wire 1 * D $end
$var wire 1 # Resetn $end
$var reg 1 + Q $end
$upscope $end
$scope module dff3 $end
$var wire 1 " Clock $end
$var wire 1 , D $end
$var wire 1 # Resetn $end
$var reg 1 - Q $end
$upscope $end
$scope module dff4 $end
$var wire 1 " Clock $end
$var wire 1 . D $end
$var wire 1 # Resetn $end
$var reg 1 / Q $end
$upscope $end
$upscope $end
$upscope $end
$enddefinitions $end
#0
$dumpvars
0/
0.
0-
0,
0+
0*
0)
0(
0'
1&
b1 %
b0 $
0#
0"
b0 !
$end
#10
1"
#15
1#
#20
1(
b11 %
b1 !
b1 $
1'
0"
#30
1"
#40
1*
b111 %
b11 !
b11 $
1)
0"
#50
1"
#60
1,
b1111 %
b111 !
b111 $
1+
0"
#70
1"
#80
1.
b11111 %
b1111 !
b1111 $
1-
0"
#90
1"
#100
0&
b11110 %
b11111 !
b11111 $
1/
0"
#110
1"
#120
0(
b11100 %
b11110 !
b11110 $
0'
0"
#130
1"
#140
0*
b11000 %
b11100 !
b11100 $
0)
0"
#150
1"
#160
0,
b10000 %
b11000 !
b11000 $
0+
0"
#170
1"
#180
0.
b0 %
b10000 !
b10000 $
0-
0"
#190
1"
#200
1&
b1 %
b0 !
b0 $
0/
0"
